hahtorch/__init__.py
hahtorch/_costs.py
hahtorch/_extract_features.py
hahtorch/_layers.py
hahtorch/_models.py
hahtorch/_version.py
hahtorch-0.0.5.dist-info/LICENSE
hahtorch-0.0.5.dist-info/METADATA
hahtorch-0.0.5.dist-info/WHEEL
hahtorch-0.0.5.dist-info/top_level.txt
hahtorch-0.0.5.dist-info/RECORD
