Metadata-Version: 2.1
Name: hahtorch
Version: 0.0.5
Summary: Hebbian/Anti-Hebbian Learning for Pytorch
Home-page: https://github.com/metehancekic/HaH.git
Author: Metehan Cekic
Author-email: metehancekic@ucsb.edu
License: MIT
Download-URL: https://github.com/metehancekic/HaH/archive/v_005.tar.gz
Keywords: Hebbian,Anti-Hebbian,Pytorch,Neuro-inspired
Platform: UNKNOWN
Classifier: Development Status :: 4 - Beta
Classifier: Intended Audience :: Developers
Classifier: Topic :: Software Development :: Build Tools
Classifier: License :: OSI Approved :: MIT License
Classifier: Programming Language :: Python :: 3.5
Classifier: Programming Language :: Python :: 3.6
Classifier: Programming Language :: Python :: 3.7
Classifier: Programming Language :: Python :: 3.8
Requires-Dist: numpy
